program_counter/program_counter.sv
module program_counter (output logic [31:0] PC,
                            input logic [31:0] PCNext,
                            input logic CLK, Reset);

always_ff @ (posedge CLK)
begin
    if (Reset) begin
        PC <= 32'h00000000;
    end
    else begin
        PC <= PCNext;
    end

end


endmodule

program_counter/program_counter_tb.sv
`timescale 1ns/1ps                                      // Define time units
`include "program_counter/program_counter.sv"           // Include pc module

module program_counter_tb;

logic [31:0] pc, pcnext;
logic clk, reset;                                       // Variable declaration
program_counter dut (pc, pcnext, clk, reset);           // Instantiate the module under test

initial begin
    $dumpfile("program_counter/program_counter_tb.vcd");// Dump variable changes in the vcd file
    $dumpvars(0, program_counter_tb);                   // Specifies which variables to dump in the vcd file
    // Initialise signals
    reset = 1;
    pcnext = 32'h00000000;

    #10;
    reset = 0;

    #10;
    pcnext = 32'h00000004;

    #10;
    pcnext = 32'h00000008;

    #10;
    pcnext = 32'h0000000C;

    #10;
    pcnext = 32'h00000010;

    #10;
    reset = 1;  // Test reset again
    pcnext = 32'h00000014;

    #10;
    reset = 0;
    pcnext = 32'h00000020;

    #20;

    $finish;
end

initial begin
    clk = 0;
    forever #5 clk = ~clk;
end

initial begin                       
    $monitor("t = %3d, pc = %h, pcnext = %h, clk = %b, reset = %b \n", $time, pc, pcnext, clk, reset);
end                                 // Print variable values on screen
endmodule

program_counter/program_counter_tb.vcd
$date
	Fri May 29 10:43:30 2026
$end
$version
	Icarus Verilog
$end
$timescale
	1ps
$end
$scope module program_counter_tb $end
$var wire 32 ! pc [31:0] $end
$var reg 1 " clk $end
$var reg 32 # pcnext [31:0] $end
$var reg 1 $ reset $end
$scope module dut $end
$var wire 1 " CLK $end
$var wire 32 % PCNext [31:0] $end
$var wire 1 $ Reset $end
$var reg 32 & PC [31:0] $end
$upscope $end
$upscope $end
$enddefinitions $end
$comment Show the parameter values. $end
$dumpall
$end
#0
$dumpvars
bx &
b0 %
1$
b0 #
0"
bx !
$end
#5000
b0 !
b0 &
1"
#10000
0"
0$
#15000
1"
#20000
0"
b100 #
b100 %
#25000
b100 !
b100 &
1"
#30000
0"
b1000 #
b1000 %
#35000
b1000 !
b1000 &
1"
#40000
0"
b1100 #
b1100 %
#45000
b1100 !
b1100 &
1"
#50000
0"
b10000 #
b10000 %
#55000
b10000 !
b10000 &
1"
#60000
0"
b10100 #
b10100 %
1$
#65000
b0 !
b0 &
1"
#70000
0"
b100000 #
b100000 %
0$
#75000
b100000 !
b100000 &
1"
