program_counter/program_counter.sv
module program_counter (output logic [31:0] PC,
                            input logic [31:0] PCNext,
                            input logic CLK, Reset);

always_ff @ (posedge CLK)
begin
    if (Reset) begin
        PC <= 32'h00000000;
    end
    else begin
        PC <= PCNext;
    end

end


endmodule

program_counter/program_counter_tb.sv
`timescale 1ns/1ps                                      // Define time units
`include "program_counter/program_counter.sv"           // Include pc module

module program_counter_tb;

logic [31:0] pc, pcnext;
logic clk, reset;                                       // Variable declaration
program_counter dut (pc, pcnext, clk, reset);           // Instantiate the module under test

initial begin
    $dumpfile("program_counter/program_counter_tb.vcd");// Dump variable changes in the vcd file
    $dumpvars(0, program_counter_tb);                   // Specifies which variables to dump in the vcd file
    // Initialise signals
    reset = 1;
    pcnext = 32'h00000000;
    #10; reset = 0;
    #5; pcnext = 32'h00000004;
    #10; pcnext = 32'h00000006;
    #10; pcnext = 32'h0000000C;
    #10; pcnext = 32'h00000010;
    #10; reset = 1; pcnext = 32'h00000018;              // Test reset again 
    #10; reset = 0; pcnext = 32'h0000001E;
    #20;

    $finish;
end

initial begin
    clk = 0;
    forever #5 clk = ~clk;
end

initial begin                       
    $monitor("t = %3d, pc = %h, pcnext = %h, clk = %b, reset = %b \n", $time, pc, pcnext, clk, reset);
end                                 // Print variable values on screen
endmodule

program_counter/program_counter_tb.vcd
$date
	Fri May 29 10:55:05 2026
$end
$version
	Icarus Verilog
$end
$timescale
	1ps
$end
$scope module program_counter_tb $end
$var wire 32 ! pc [31:0] $end
$var reg 1 " clk $end
$var reg 32 # pcnext [31:0] $end
$var reg 1 $ reset $end
$scope module dut $end
$var wire 1 " CLK $end
$var wire 32 % PCNext [31:0] $end
$var wire 1 $ Reset $end
$var reg 32 & PC [31:0] $end
$upscope $end
$upscope $end
$enddefinitions $end
$comment Show the parameter values. $end
$dumpall
$end
#0
$dumpvars
bx &
b0 %
1$
b0 #
0"
bx !
$end
#5000
b0 !
b0 &
1"
#10000
0"
0$
#15000
b100 !
b100 &
1"
b100 #
b100 %
#20000
0"
#25000
b110 !
b110 &
1"
b110 #
b110 %
#30000
0"
#35000
b1100 !
b1100 &
1"
b1100 #
b1100 %
#40000
0"
#45000
b10000 !
b10000 &
1"
b10000 #
b10000 %
#50000
0"
#55000
b0 !
b0 &
1"
b11000 #
b11000 %
1$
#60000
0"
#65000
b11110 !
b11110 &
1"
b11110 #
b11110 %
0$
