alu/alu.sv
module alu (output logic [31:0] ALUResult,
                output logic Zero, Negative,
                input logic [31:0] A, B,
                input logic [4:0] ALUControl);

logic [31:0] y_add, y_sub, y_or, y_and, y_sll, y_srl, y_slt;

assign y_add = A + B;
assign y_sub = A - B;
assign y_or = A | B;
assign y_and = A & B;
assign y_sll = A << B;
assign y_srl = A >> B;
assign y_slt = {31'b0, y_sub[31]};      // zero extend if A - B is negative

always_comb begin
    casez (ALUControl)
        5'b?0?10: ALUResult = y_add;    // add
        5'b?1?10: ALUResult = y_sub;    // subtract
        5'b??111: ALUResult = y_or;     // bitwise OR
        5'b??011: ALUResult = y_and;    // bitwise AND
        5'b0??00: ALUResult = y_sll;    // shift left logical
        5'b1??00: ALUResult = y_srl;    // shift right logical
        5'b?1?01: ALUResult = y_slt;    // set less than

        default: ALUResult = 32'bx;
        
    endcase
end

assign Negative = ALUResult[31];
assign Zero = ~|ALUResult;

endmodule

alu/alu_tb.sv
`timescale 1ns/1ps
`include "alu/alu.sv"

module alu_tb;

logic signed [31:0] aluresult, a, b;
logic [4:0] alucontrol;
logic zero, negative;
alu dut (aluresult, zero, negative, a, b, alucontrol);

initial begin
    $dumpfile("alu/alu_tb.vcd");
    $dumpvars(0, alu_tb);
    a = 32'd100; b = 32'd520;
    alucontrol = 5'b10010; #10;             // add
    alucontrol = 5'b10110; #10;             // add (X bits varied)
    alucontrol = 5'b01010; #10;             // subtract, negative (true)
    a = 32'd600; #10;                       // subtract, negative (false)
    a = 32'd520; #10;                       // subtract, zero (true)
    a = 32'd700; #10;                       // subtract, negative (false)
    alucontrol = 5'b10111; #10;             // bitwise OR
    alucontrol = 5'b01111; #10;             // bitwise OR (X bits varied)
    alucontrol = 5'b01011; #10;             // bitwise AND
    b = 32'd3; alucontrol = 5'b01000; #10;  // shift left logical
    alucontrol = 5'b10100; #10;             // shift right logical
    alucontrol = 5'b01101; #10;             // set less than (false)
    b = 32'd1000; #10;                      // set less than (true)

    $finish;
end

initial begin
    $monitor("t = %3d, aluresult = %b (%4d), zero = %b, negative = %b, \
    a = %b (%3d), b = %b (%4d), alucontrol = %b \n",
    $time, aluresult, aluresult, zero, negative, a, a, b, b, alucontrol);
end

endmodule

alu/alu_tb.vcd
$date
	Sat May 30 11:52:18 2026
$end
$version
	Icarus Verilog
$end
$timescale
	1ps
$end
$scope module alu_tb $end
$var wire 1 ! zero $end
$var wire 1 " negative $end
$var wire 32 # aluresult [31:0] $end
$var reg 32 $ a [31:0] $end
$var reg 5 % alucontrol [4:0] $end
$var reg 32 & b [31:0] $end
$scope module dut $end
$var wire 32 ' A [31:0] $end
$var wire 5 ( ALUControl [4:0] $end
$var wire 32 ) B [31:0] $end
$var wire 32 * y_and [31:0] $end
$var wire 32 + y_or [31:0] $end
$var wire 32 , y_sub [31:0] $end
$var wire 32 - y_srl [31:0] $end
$var wire 32 . y_slt [31:0] $end
$var wire 32 / y_sll [31:0] $end
$var wire 32 0 y_add [31:0] $end
$var wire 1 ! Zero $end
$var wire 1 " Negative $end
$var reg 32 1 ALUResult [31:0] $end
$upscope $end
$upscope $end
$enddefinitions $end
$comment Show the parameter values. $end
$dumpall
$end
#0
$dumpvars
b1001101100 1
b1001101100 0
b0 /
b1 .
b0 -
b11111111111111111111111001011100 ,
b1001101100 +
b0 *
b1000001000 )
b10010 (
b1100100 '
b1000001000 &
b10010 %
b1100100 $
b1001101100 #
0"
0!
$end
#10000
b10110 %
b10110 (
#20000
1"
b11111111111111111111111001011100 #
b11111111111111111111111001011100 1
b1010 %
b1010 (
#30000
0"
b1001011000 +
b1000001000 *
b0 .
b1010000 #
b1010000 1
b10001100000 0
b1010000 ,
b1001011000 $
b1001011000 '
#40000
b1000001000 +
1!
b0 #
b0 1
b10000010000 0
b0 ,
b1000001000 $
b1000001000 '
#50000
b1010111100 +
0!
b10110100 #
b10110100 1
b10011000100 0
b10110100 ,
b1010111100 $
b1010111100 '
#60000
b1010111100 #
b1010111100 1
b10111 %
b10111 (
#70000
b1111 %
b1111 (
#80000
b1000001000 #
b1000001000 1
b1011 %
b1011 (
#90000
b1010111111 +
b0 *
b1010111100000 #
b1010111100000 1
b1000 %
b1000 (
b1010111111 0
b1010111001 ,
b1010111100000 /
b1010111 -
b11 &
b11 )
#100000
b1010111 #
b1010111 1
b10100 %
b10100 (
#110000
1!
b0 #
b0 1
b1101 %
b1101 (
#120000
0!
b1 #
b1 1
b1111111100 +
b1010101000 *
b1 .
b11010100100 0
b11111111111111111111111011010100 ,
b0 /
b0 -
b1111101000 &
b1111101000 )
