control_unit/control_unit.sv
module control_unit (output logic MemWrite, ALUSrc, RegWrite,
                        output logic [4:0] ALUControl, 
                        output logic [2:0] ImmSrc,
                        output logic [1:0] PCSrc, ResultSrc,
                        input logic [31:0] Instr,
                        input logic Zero, Negative);

logic [6:0] opcode;
logic [2:0] funct3;
logic [6:0] funct7;

assign opcode = Instr[6:0];
assign funct3 = Instr[14:12];
assign funct7 = Instr[31:25];

always_comb begin
    MemWrite = (opcode == 7'b0100011 && funct3 == 3'h2) ? 1 : 0; // only sw needs MemWrite = 1
    RegWrite = (opcode[5:0] == 6'b100011) ? 0 : 1;               // only sw, beq, bne, blt and bge need RegWrite = 0

    case (opcode)
        7'b0110011: begin
            ImmSrc = 3'bxxx;
            ALUSrc = 1'b0;
            ResultSrc = 2'b00;
            PCSrc = 2'b00;
            case (funct3)
                3'h0: ALUControl = (funct7 == 7'h00) ? 5'bx0x10 : 5'bx1x10; // add/sub
                3'h6: ALUControl = 5'bxx111;                                // or
                3'h7: ALUControl = 5'bxx011;                                // and
                3'h1: ALUControl = 5'b0xx00;                                // sll
                3'h5: ALUControl = 5'b1xx00;                                // srl
                3'h2: ALUControl = 5'bx1x01;                                // slt
                default: ALUControl = 5'bxxxxx;
            endcase
        end

        7'b0010011: begin
            ImmSrc = 3'b000;
            ALUSrc = 1'b1;
            ResultSrc = 2'b00;
            PCSrc = 2'b00;
            case (funct3)
                3'h0: ALUControl = 5'bx0x10;            // addi
                3'h6: ALUControl = 5'bxx111;            // ori
                3'h7: ALUControl = 5'bxx011;            // andi
                3'h1: ALUControl = 5'b0xx00;            // slli
                3'h5: ALUControl = 5'b1xx00;            // srli
                3'h2: ALUControl = 5'bx1x01;            // slti
                default: ALUControl = 5'bxxxxx;
            endcase
        end

        7'b0000011: begin       // lw
            ImmSrc = 3'b000;
            ALUSrc = 1'b1;
            ALUControl = 5'bx0x10;
            ResultSrc = 2'b01;
            PCSrc = 2'b00;
        end

        7'b0100011: begin       // sw
            ImmSrc = 3'b001;
            ALUSrc = 1'b1;
            ALUControl = 5'bx0x10;
            ResultSrc = 2'bxx;
            PCSrc = 2'b00;
        end

        7'b1100011: begin
            ImmSrc = 3'b010;
            ALUSrc = 1'b0;
            ALUControl = 5'bx1x10;
            ResultSrc = 2'bxx;
            case (funct3)
                3'h0: PCSrc = {1'b0, Zero};             // beq
                3'h1: PCSrc = {1'b0, ~Zero};            // bne
                3'h4: PCSrc = {1'b0, Negative};         // blt
                3'h5: PCSrc = {1'b0, ~Negative};        // bge
                default: PCSrc = 2'bxx;
            endcase
        end

        7'b1101111: begin       // jal
            ImmSrc = 3'b100;
            ALUSrc = 1'bx;
            ALUControl = 5'bxxxxx;
            ResultSrc = 2'b10;
            PCSrc = 2'b01;
        end

        7'b1100111: begin       // jalr
            ImmSrc = 3'b000;
            ALUSrc = 1'b1;
            ALUControl = 5'bx0x10;
            ResultSrc = 2'b10;
            PCSrc = 2'b10;
        end

        7'b0110111: begin       // lui
            ImmSrc = 3'b011;
            ALUSrc = 1'bx;
            ALUControl = 5'bxxxxx;
            ResultSrc = 2'b11;
            PCSrc = 2'b00;
        end

        default: begin
            ImmSrc = 3'bxxx;
            ALUSrc = 1'bx;
            ALUControl = 5'bxxxxx;
            ResultSrc = 2'bxx;
            PCSrc = 2'bxx;
        end
    endcase
end

endmodule

control_unit/control_unit_tb.sv
`timescale 1ns/1ps
`include "control_unit/control_unit.sv"

module control_unit_tb;

logic memwrite, alusrc, regwrite, zero, negative;
logic [4:0] alucontrol;
logic [2:0] immsrc;
logic [1:0] pcsrc, resultsrc;
logic [31:0] instr;
control_unit dut (memwrite, alusrc, regwrite, alucontrol, immsrc, pcsrc, resultsrc, instr, zero, negative);


initial begin
    $dumpfile("control_unit/control_unit_tb.vcd");
    $dumpvars(0, control_unit_tb);

    instr = 32'b0000000xxxxxxxxxx000xxxxx0110011; #10;  // add
    instr = 32'b0100000xxxxxxxxxx000xxxxx0110011; #10;  // sub
    instr = 32'b0000000xxxxxxxxxx110xxxxx0110011; #10;  // or
    instr = 32'b0000000xxxxxxxxxx111xxxxx0110011; #10;  // and
    instr = 32'b0000000xxxxxxxxxx001xxxxx0110011; #10;  // sll
    instr = 32'b0000000xxxxxxxxxx101xxxxx0110011; #10;  // srl
    instr = 32'b0000000xxxxxxxxxx010xxxxx0110011; #10;  // slt

    instr = 32'bxxxxxxxxxxxxxxxxx000xxxxx0010011; #10;  // addi
    instr = 32'bxxxxxxxxxxxxxxxxx110xxxxx0010011; #10;  // ori
    instr = 32'bxxxxxxxxxxxxxxxxx111xxxxx0010011; #10;  // andi
    instr = 32'bxxxxxxxxxxxxxxxxx001xxxxx0010011; #10;  // slli
    instr = 32'bxxxxxxxxxxxxxxxxx101xxxxx0010011; #10;  // srli
    instr = 32'bxxxxxxxxxxxxxxxxx010xxxxx0010011; #10;  // slti

    instr = 32'bxxxxxxxxxxxxxxxxx010xxxxx0000011; #10;  // lw
    instr = 32'bxxxxxxxxxxxxxxxxx010xxxxx0100011; #10;  // sw
    
    instr = 32'bxxxxxxxxxxxxxxxxx000xxxxx1100011;       // beq, zero = 0 
    zero = 1'b0; #10;
    instr = 32'bxxxxxxxxxxxxxxxxx000xxxxx1100011;       // beq, zero = 1
    zero = 1'b1; #10;
    
    instr = 32'bxxxxxxxxxxxxxxxxx001xxxxx1100011;       // bne, zero = 0
    zero = 1'b0; #10;
    instr = 32'bxxxxxxxxxxxxxxxxx001xxxxx1100011;       // bne, zero = 1
    zero = 1'b1; #10;

    instr = 32'bxxxxxxxxxxxxxxxxx100xxxxx1100011;       // blt, negative = 0
    negative = 1'b0; #10;
    instr = 32'bxxxxxxxxxxxxxxxxx100xxxxx1100011;       // blt, negative = 1
    negative = 1'b1; #10;

    instr = 32'bxxxxxxxxxxxxxxxxx101xxxxx1100011; #10;  // bge, negative = 0
    negative = 1'b0; #10;
    instr = 32'bxxxxxxxxxxxxxxxxx101xxxxx1100011; #10;  // bge, negative = 1
    negative = 1'b1; #10;

    instr = 32'b0000000xxxxxxxxxx000xxxxx1101111; #10;  // jal
    instr = 32'b0100000xxxxxxxxxx000xxxxx1100111; #10;  // jalr
    instr = 32'b0000000xxxxxxxxxx110xxxxx0110111; #10;  // lui

    $finish;
end

initial begin
    $monitor("t = %3d, instr = %b, zero = %b, negative = %b, regwrite = %b, \
    immsrc = %b, alusrc = %b, alucontrol = %b, memwrite = %b, resultsrc = %b \
    pcsrc = %b, \n",
    $time, instr, zero, negative, regwrite, immsrc, alusrc, alucontrol, memwrite, 
        resultsrc, pcsrc);
end

endmodule

control_unit/control_unit_tb.vcd
$date
	Sat May 30 15:46:20 2026
$end
$version
	Icarus Verilog
$end
$timescale
	1ps
$end
$scope module control_unit_tb $end
$var wire 2 ! resultsrc [1:0] $end
$var wire 1 " regwrite $end
$var wire 2 # pcsrc [1:0] $end
$var wire 1 $ memwrite $end
$var wire 3 % immsrc [2:0] $end
$var wire 1 & alusrc $end
$var wire 5 ' alucontrol [4:0] $end
$var reg 32 ( instr [31:0] $end
$var reg 1 ) negative $end
$var reg 1 * zero $end
$scope module dut $end
$var wire 32 + Instr [31:0] $end
$var wire 1 ) Negative $end
$var wire 1 * Zero $end
$var wire 7 , opcode [6:0] $end
$var wire 7 - funct7 [6:0] $end
$var wire 3 . funct3 [2:0] $end
$var wire 1 " RegWrite $end
$var wire 1 $ MemWrite $end
$var reg 5 / ALUControl [4:0] $end
$var reg 1 & ALUSrc $end
$var reg 3 0 ImmSrc [2:0] $end
$var reg 2 1 PCSrc [1:0] $end
$var reg 2 2 ResultSrc [1:0] $end
$upscope $end
$upscope $end
$enddefinitions $end
$comment Show the parameter values. $end
$dumpall
$end
#0
$dumpvars
b0 2
b0 1
bx 0
bx0x10 /
b0 .
b0 -
b110011 ,
b0xxxxxxxxxx000xxxxx0110011 +
x*
x)
b0xxxxxxxxxx000xxxxx0110011 (
bx0x10 '
0&
bx %
0$
b0 #
1"
b0 !
$end
#10000
bx1x10 '
bx1x10 /
b100000 -
b100000xxxxxxxxxx000xxxxx0110011 (
b100000xxxxxxxxxx000xxxxx0110011 +
#20000
bx111 '
bx111 /
b110 .
b0 -
b0xxxxxxxxxx110xxxxx0110011 (
b0xxxxxxxxxx110xxxxx0110011 +
#30000
bx011 '
bx011 /
b111 .
b0xxxxxxxxxx111xxxxx0110011 (
b0xxxxxxxxxx111xxxxx0110011 +
#40000
b0xx00 '
b0xx00 /
b1 .
b0xxxxxxxxxx001xxxxx0110011 (
b0xxxxxxxxxx001xxxxx0110011 +
#50000
b1xx00 '
b1xx00 /
b101 .
b0xxxxxxxxxx101xxxxx0110011 (
b0xxxxxxxxxx101xxxxx0110011 +
#60000
bx1x01 '
bx1x01 /
b10 .
b0xxxxxxxxxx010xxxxx0110011 (
b0xxxxxxxxxx010xxxxx0110011 +
#70000
bx0x10 '
bx0x10 /
1&
b0 %
b0 0
b10011 ,
b0 .
bx -
bx000xxxxx0010011 (
bx000xxxxx0010011 +
#80000
bx111 '
bx111 /
b110 .
bx110xxxxx0010011 (
bx110xxxxx0010011 +
#90000
bx011 '
bx011 /
b111 .
bx111xxxxx0010011 (
bx111xxxxx0010011 +
#100000
b0xx00 '
b0xx00 /
b1 .
bx001xxxxx0010011 (
bx001xxxxx0010011 +
#110000
b1xx00 '
b1xx00 /
b101 .
bx101xxxxx0010011 (
bx101xxxxx0010011 +
#120000
bx1x01 '
bx1x01 /
b10 .
bx010xxxxx0010011 (
bx010xxxxx0010011 +
#130000
b1 !
b1 2
bx0x10 '
bx0x10 /
b11 ,
bx010xxxxx0000011 (
bx010xxxxx0000011 +
#140000
1$
0"
bx !
bx 2
b1 %
b1 0
b100011 ,
bx010xxxxx0100011 (
bx010xxxxx0100011 +
#150000
0$
bx1x10 '
bx1x10 /
0&
b10 %
b10 0
b1100011 ,
b0 .
0*
bx000xxxxx1100011 (
bx000xxxxx1100011 +
#160000
b1 #
b1 1
1*
#170000
b1 .
0*
bx001xxxxx1100011 (
bx001xxxxx1100011 +
#180000
b0 #
b0 1
1*
#190000
b100 .
0)
bx100xxxxx1100011 (
bx100xxxxx1100011 +
#200000
b1 #
b1 1
1)
#210000
b0 #
b0 1
b101 .
bx101xxxxx1100011 (
bx101xxxxx1100011 +
#220000
b1 #
b1 1
0)
#240000
b0 #
b0 1
1)
#250000
1"
b1 #
b1 1
b10 !
b10 2
bx '
bx /
x&
b100 %
b100 0
b1101111 ,
b0 .
b0 -
b0xxxxxxxxxx000xxxxx1101111 (
b0xxxxxxxxxx000xxxxx1101111 +
#260000
b10 #
b10 1
bx0x10 '
bx0x10 /
1&
b0 %
b0 0
b1100111 ,
b100000 -
b100000xxxxxxxxxx000xxxxx1100111 (
b100000xxxxxxxxxx000xxxxx1100111 +
#270000
b0 #
b0 1
b11 !
b11 2
bx '
bx /
x&
b11 %
b11 0
b110111 ,
b110 .
b0 -
b0xxxxxxxxxx110xxxxx0110111 (
b0xxxxxxxxxx110xxxxx0110111 +
